pydentity/__init__.py
pydentity/_meta/__init__.py
pydentity/authentication/__init__.py
pydentity/authentication/bearer/__init__.py
pydentity/authentication/bearer/handlers.py
pydentity/authentication/bearer/param.py
pydentity/authentication/builder.py
pydentity/authentication/cookie/__init__.py
pydentity/authentication/cookie/handlers.py
pydentity/authentication/cookie/param.py
pydentity/authentication/exc.py
pydentity/authentication/interfaces/__init__.py
pydentity/authentication/options.py
pydentity/authentication/provider.py
pydentity/authentication/result.py
pydentity/authentication/scheme.py
pydentity/authentication/scheme_builder.py
pydentity/authorization/__init__.py
pydentity/authorization/builder.py
pydentity/authorization/context.py
pydentity/authorization/exc.py
pydentity/authorization/interfaces/__init__.py
pydentity/authorization/options.py
pydentity/authorization/param.py
pydentity/authorization/policy.py
pydentity/authorization/policy_builder.py
pydentity/authorization/provider.py
pydentity/contrib/__init__.py
pydentity/contrib/fastapi/__init__.py
pydentity/contrib/fastapi/base.py
pydentity/contrib/fastapi/guard.py
pydentity/contrib/fastapi/middleware.py
pydentity/contrib/litestar/__init__.py
pydentity/contrib/litestar/base.py
pydentity/contrib/litestar/guard.py
pydentity/contrib/litestar/middleware.py
pydentity/contrib/litestar/plugin.py
pydentity/contrib/sqlalchemy/__init__.py
pydentity/contrib/sqlalchemy/base/__init__.py
pydentity/contrib/sqlalchemy/base/abstract.py
pydentity/contrib/sqlalchemy/base/model.py
pydentity/contrib/sqlalchemy/fields.py
pydentity/contrib/sqlalchemy/models.py
pydentity/contrib/sqlalchemy/stores/__init__.py
pydentity/contrib/sqlalchemy/stores/role_store.py
pydentity/contrib/sqlalchemy/stores/user_store.py
pydentity/contrib/tortoise/__init__.py
pydentity/contrib/tortoise/base/__init__.py
pydentity/contrib/tortoise/base/abstract.py
pydentity/contrib/tortoise/base/model.py
pydentity/contrib/tortoise/fields.py
pydentity_core-0.4.0.dist-info/METADATA
pydentity_core-0.4.0.dist-info/WHEEL
pydentity_core-0.4.0.dist-info/RECORD
