Metadata-Version: 2.1
Name: pydentity-core
Version: 0.4.0
Summary: 
Home-page: https://github.com/udachin077/pydentity-core
License: MIT
Author: Udachin Ivan
Author-email: pypi.udachin@yandex.ru
Requires-Python: >=3.12,<4.0
Classifier: License :: OSI Approved :: MIT License
Classifier: Programming Language :: Python :: 3
Classifier: Programming Language :: Python :: 3.12
Classifier: Programming Language :: Python :: 3.13
Provides-Extra: machineid
Requires-Dist: cryptography (>=44.0.0,<45.0.0)
Requires-Dist: email-validator (>=2.2.0,<3.0.0)
Requires-Dist: itsdangerous (>=2.2.0,<3.0.0)
Requires-Dist: pwdlib[argon2,bcrypt] (>=0.2.1,<0.3.0)
Requires-Dist: py-machineid (>=0.6.0,<0.7.0) ; extra == "machineid"
Requires-Dist: pyjwt (>=2.10.1,<3.0.0)
Requires-Dist: pyotp (>=2.9.0,<3.0.0)
Requires-Dist: uuid7 (>=0.1.0,<0.2.0)
Project-URL: Repository, https://github.com/udachin077/pydentity-core.git
